{
    "schema_version":  1,
    "generated_by":  "scripts/embed-ui.ps1",
    "build_nonce":  "5d8e4c34-52cc-4133-8964-85a2fb1fd07b",
    "embedded_at_utc":  "2026-03-15T07:01:11Z",
    "ui_source_latest_write_utc":  "2026-03-15T07:01:11Z",
    "dist_hash_sha256":  "437016efcf78a80a16dbb7ef85a7ea79f867d5fb7dd25bfe799cdf785dfa48df",
    "embedded_hash_sha256":  "70598b94289bf9725558ecace9c4a236869c01eba8c3e662a13d7e8661947f2a",
    "dist_dir":  "D:\\SIPTunnel\\gateway-ui\\dist",
    "embedded_dir":  "D:\\SIPTunnel\\gateway-server\\internal\\server\\embedded-ui"
}
